{
    "archives": {
        "UpdateProfile": {
            "DEFAULT": "system_health_desktop_8c7c864e79.wprgo"
        },
        "browse:news:hackernews:2020": {
            "DEFAULT": "system_health_desktop_c72fda288b.wprgo"
        },
        "browse:search:google:2020": {
            "DEFAULT": "system_health_desktop_20c4fe6ace.wprgo"
        },
        "load:media:youtube:2018": {
            "DEFAULT": "system_health_desktop_81f7c27d9f.wprgo"
        },
        "load:ntp:brave_news:2024": {
            "DEFAULT": "system_health_desktop_8c7c864e79.wprgo"
        },
        "load:site:amazon:2024": {
            "DEFAULT": "system_health_desktop_8c7c864e79.wprgo"
        },
        "load:site:bbc:2023": {
            "DEFAULT": "system_health_desktop_8c7c864e79.wprgo"
        },
        "load:site:brave_search:2023": {
            "DEFAULT": "system_health_desktop_8c7c864e79.wprgo"
        },
        "load:site:cnn:2023": {
            "DEFAULT": "system_health_desktop_8c7c864e79.wprgo"
        },
        "load:site:example:2023": {
            "DEFAULT": "system_health_desktop_8c7c864e79.wprgo"
        },
        "load:site:google:2023": {
            "DEFAULT": "system_health_desktop_8c7c864e79.wprgo"
        },
        "load:site:hackernews:2024": {
            "DEFAULT": "system_health_desktop_8c7c864e79.wprgo"
        },
        "load:site:imdb:2024": {
            "DEFAULT": "system_health_desktop_8c7c864e79.wprgo"
        },
        "load:site:pinterest:2024": {
            "DEFAULT": "system_health_desktop_8c7c864e79.wprgo"
        },
        "load:site:twitter:2023": {
            "DEFAULT": "system_health_desktop_8c7c864e79.wprgo"
        },
        "load:site:wikipedia:2023": {
            "DEFAULT": "system_health_desktop_8c7c864e79.wprgo"
        },
        "multitab_load:site:example.com:2024": {
            "DEFAULT": "system_health_desktop_8c7c864e79.wprgo"
        }
    },
    "description": "Describes the Web Page Replay archives for a story set. Don't edit by hand! Use record_wpr for updating.",
    "platform_specific": true
}
