[
  {
    "image": "EAFF_JA_soccer_Background_final.jpg",
    "center": 1280,
    "credit": {
      "name": "EAFF 2019",
      "url": "https://eaff.com/competitions/eaff2019/"
    },
    "dates": {
      "start": "2019-11-25T00:00:13+09:00",
      "end": "2019-12-18T00:00:00+09:00"
    },
    "regions": [
      "JP",
      "CN",
      "KR",
      "KP",
      "TW",
      "MN",
      "MO",
      "GU",
      "MP",
      "SG",
      "IN",
      "PK",
      "MV",
      "BD",
      "BT",
      "NP",
      "UZ"
    ]
  }
]