<vector xmlns:android="http://schemas.android.com/apk/res/android"
    xmlns:aapt="http://schemas.android.com/aapt"
    android:width="39dp"
    android:height="50dp"
    android:viewportWidth="39"
    android:viewportHeight="50">
    <group>
        <clip-path android:pathData="M0.5,0.5342h38v48.8571h-38z" />
        <group>
            <clip-path android:pathData="M2.7619,0.9866h33.6605v44.3333h-33.6605z" />
            <path
                android:fillType="evenOdd"
                android:pathData="M25.5443,0.9866L36.4224,12.0699V42.036C36.4224,43.8503 34.9528,45.3199 33.1384,45.3199H6.0458C4.2315,45.3199 2.7619,43.8503 2.7619,42.036V4.2705C2.7619,2.4561 4.2315,0.9866 6.0458,0.9866H25.5443Z">
                <aapt:attr name="android:fillColor">
                    <gradient
                        android:endX="42.9627"
                        android:endY="42.2557"
                        android:startX="15.1793"
                        android:startY="-4.04198"
                        android:type="linear">
                        <item
                            android:color="#FFD9D9D9"
                            android:offset="0" />
                        <item
                            android:color="#FFFFFFFF"
                            android:offset="0.734375" />
                    </gradient>
                </aapt:attr>
            </path>
            <path
                android:fillColor="#D1D1D1"
                android:fillType="evenOdd"
                android:pathData="M35.4153,12.0698L25.5445,2.0128V9.8122C25.5445,11.6266 27.0141,13.0962 28.8284,13.0962H36.4226L36.4225,13.096V12.0698H35.4153Z" />
            <path
                android:fillType="evenOdd"
                android:pathData="M25.5445,0.9866L36.4226,12.0699H29.6494C27.1865,12.0699 25.5445,9.8122 25.5445,7.4518L25.5445,0.9866Z">
                <aapt:attr name="android:fillColor">
                    <gradient
                        android:endX="36.4226"
                        android:endY="14.0198"
                        android:startX="32.7281"
                        android:startY="-1.88688"
                        android:type="linear">
                        <item
                            android:color="#FFC0C0C0"
                            android:offset="0" />
                        <item
                            android:color="#FFFFFFFF"
                            android:offset="1" />
                    </gradient>
                </aapt:attr>
            </path>
            <path
                android:fillType="evenOdd"
                android:pathData="M28.4095,19.7021L28.9118,18.4677C28.9118,18.4677 28.2725,17.7819 27.4962,17.0047C26.72,16.2274 25.0761,16.6846 25.0761,16.6846L23.204,14.558H19.9163H16.6286L14.7565,16.6846C14.7565,16.6846 13.1126,16.2274 12.3364,17.0047C11.5601,17.7819 10.9209,18.4677 10.9209,18.4677L11.4231,19.7021L10.7839,21.5309C10.7839,21.5309 12.664,28.661 12.8843,29.5318C13.3181,31.2462 13.6149,31.9092 14.8478,32.7778C16.0807,33.6465 18.3181,35.1552 18.6834,35.3838C19.0487,35.6124 19.5054,36.0018 19.9163,36.0018C20.3273,36.0018 20.7839,35.6124 21.1492,35.3838C21.5145,35.1552 23.7519,33.6465 24.9848,32.7778C26.2177,31.9092 26.5145,31.2462 26.9483,29.5318C27.1686,28.661 29.0488,21.5309 29.0488,21.5309L28.4095,19.7021Z">
                <aapt:attr name="android:fillColor">
                    <gradient
                        android:endX="29.0488"
                        android:endY="36.1531"
                        android:startX="10.7839"
                        android:startY="36.1531"
                        android:type="linear">
                        <item
                            android:color="#FFFF5500"
                            android:offset="0" />
                        <item
                            android:color="#FFFF5500"
                            android:offset="0.409877" />
                        <item
                            android:color="#FFFF2000"
                            android:offset="0.581981" />
                        <item
                            android:color="#FFFF2000"
                            android:offset="1" />
                    </gradient>
                </aapt:attr>
            </path>
            <path
                android:fillColor="#ffffff"
                android:fillType="evenOdd"
                android:pathData="M22.2451,18.422C22.519,18.422 24.551,18.0334 24.551,18.0334C24.551,18.0334 26.959,20.948 26.959,21.5709C26.959,22.0859 26.752,22.2875 26.5081,22.5249C26.457,22.5747 26.4043,22.626 26.3516,22.6821L24.546,24.6018C24.5281,24.6208 24.5082,24.6409 24.4871,24.6621C24.3068,24.8435 24.0415,25.1107 24.2287,25.5544C24.2412,25.5841 24.2541,25.6142 24.2672,25.6448C24.4725,26.1256 24.726,26.719 24.4033,27.3205C24.0601,27.9602 23.4722,28.3871 23.0955,28.3166C22.7188,28.2459 21.8341,27.783 21.5088,27.5716C21.1834,27.3601 20.1523,26.5086 20.1523,26.1828C20.1523,25.9111 20.8938,25.4591 21.2542,25.2395C21.3258,25.1958 21.3824,25.1613 21.4151,25.1392C21.4523,25.1142 21.5145,25.0755 21.591,25.0278C21.9199,24.8233 22.5137,24.4539 22.5286,24.2901C22.547,24.0882 22.54,24.0289 22.2749,23.5301C22.2186,23.424 22.1526,23.3103 22.0844,23.1929C21.832,22.7581 21.5494,22.2712 21.612,21.9224C21.6826,21.5287 22.2987,21.3029 22.8207,21.1117C22.8859,21.0878 22.9496,21.0645 23.0107,21.0414C23.163,20.9838 23.3544,20.912 23.5543,20.837C24.0754,20.6416 24.6544,20.4244 24.7499,20.3804C24.8821,20.3193 24.8479,20.2612 24.4476,20.2232C24.3946,20.2182 24.3288,20.2112 24.2532,20.2031C23.7577,20.1504 22.8437,20.0532 22.3994,20.1772C22.312,20.2016 22.214,20.2281 22.1113,20.256C21.6121,20.3913 21.0003,20.5572 20.9415,20.6528C20.9312,20.6696 20.9211,20.684 20.9116,20.6975C20.8553,20.7776 20.8187,20.8297 20.8809,21.1698C20.8994,21.2711 20.9375,21.4703 20.9846,21.7166C21.1225,22.4377 21.3376,23.5625 21.3647,23.8152C21.3685,23.8505 21.3727,23.8847 21.3767,23.9175C21.4112,24.1994 21.4341,24.387 21.1072,24.4619C21.0799,24.4681 21.0513,24.4747 21.0216,24.4815C20.6526,24.5663 20.1117,24.6906 19.9163,24.6906C19.7208,24.6906 19.1794,24.5662 18.8105,24.4814C18.7809,24.4746 18.7525,24.4681 18.7254,24.4619C18.3984,24.387 18.4214,24.1994 18.4559,23.9175C18.4599,23.8846 18.464,23.8505 18.4678,23.8152C18.495,23.5621 18.7107,22.4345 18.8485,21.7135C18.8954,21.4686 18.9332,21.2706 18.9517,21.1698C19.0139,20.8298 18.9772,20.7776 18.921,20.6976C18.9115,20.684 18.9014,20.6696 18.8911,20.6528C18.8323,20.5572 18.2206,20.3914 17.7214,20.256C17.6186,20.2282 17.5206,20.2016 17.4332,20.1772C16.9889,20.0532 16.075,20.1504 15.5794,20.2031C15.5038,20.2112 15.4379,20.2182 15.385,20.2232C14.9847,20.2612 14.9505,20.3193 15.0827,20.3804C15.1781,20.4244 15.7568,20.6415 16.2778,20.8368C16.4779,20.9119 16.6695,20.9837 16.8219,21.0414C16.883,21.0645 16.9468,21.0878 17.012,21.1117C17.5339,21.303 18.15,21.5287 18.2206,21.9224C18.2832,22.2711 18.0006,22.7579 17.7482,23.1927C17.68,23.3102 17.614,23.4239 17.5577,23.5301C17.2926,24.0289 17.2856,24.0882 17.304,24.2901C17.3188,24.4538 17.9124,24.8231 18.2413,25.0277C18.318,25.0754 18.3803,25.1141 18.4175,25.1392C18.4501,25.1613 18.5067,25.1957 18.5782,25.2394C18.9385,25.459 19.6803,25.9111 19.6803,26.1828C19.6803,26.5086 18.6492,27.3601 18.3238,27.5716C17.9985,27.783 17.1138,28.2459 16.7371,28.3166C16.3603,28.3871 15.7724,27.9602 15.4292,27.3205C15.1067,26.7191 15.36,26.1257 15.5653,25.6449C15.5784,25.6143 15.5913,25.5841 15.6038,25.5544C15.7911,25.1106 15.5257,24.8435 15.3454,24.662C15.3243,24.6408 15.3044,24.6208 15.2866,24.6018L13.481,22.6821C13.4282,22.626 13.3756,22.5747 13.3245,22.525C13.0806,22.2875 12.8735,22.086 12.8735,21.5709C12.8735,20.948 15.2816,18.0334 15.2816,18.0334C15.2816,18.0334 17.3135,18.422 17.5875,18.422C17.8061,18.422 18.2283,18.2764 18.6683,18.1247C18.7798,18.0863 18.8923,18.0474 19.003,18.0105C19.551,17.8276 19.9163,17.8263 19.9163,17.8263C19.9163,17.8263 20.2816,17.8276 20.8295,18.0105C20.9402,18.0474 21.0528,18.0863 21.1642,18.1247C21.6043,18.2764 22.0264,18.422 22.2451,18.422ZM21.8963,28.7313C22.3259,28.9529 22.6306,29.1101 22.7458,29.1823C22.8949,29.2757 22.8039,29.4519 22.6682,29.548C22.5324,29.6441 20.7077,31.0588 20.5306,31.2152C20.5079,31.2352 20.4839,31.2569 20.4589,31.2795C20.2883,31.4335 20.0706,31.6299 19.9163,31.6299C19.7619,31.6299 19.5442,31.4333 19.3735,31.2793C19.3486,31.2568 19.3246,31.2352 19.302,31.2152C19.1249,31.0588 17.3002,29.6441 17.1644,29.548C17.0286,29.4519 16.9378,29.2757 17.0868,29.1823C17.2021,29.1101 17.5071,28.9527 17.9371,28.7309C18.0631,28.6658 18.1999,28.5953 18.3458,28.5197C18.9892,28.1863 19.7912,27.9028 19.9163,27.9028C20.0415,27.9028 20.8434,28.1863 21.4869,28.5197C21.6331,28.5954 21.7701,28.6661 21.8963,28.7313Z" />
            <path
                android:fillType="evenOdd"
                android:pathData="M25.0761,16.6846L23.204,14.558H19.9163H16.6286L14.7565,16.6846C14.7565,16.6846 13.1126,16.2274 12.3364,17.0047C12.3364,17.0047 14.5282,16.8066 15.2816,18.0333C15.2816,18.0333 17.3135,18.422 17.5875,18.422C17.8615,18.422 18.4551,18.1934 19.003,18.0105C19.551,17.8276 19.9163,17.8263 19.9163,17.8263C19.9163,17.8263 20.2816,17.8276 20.8295,18.0105C21.3775,18.1934 21.9711,18.422 22.2451,18.422C22.519,18.422 24.551,18.0333 24.551,18.0333C25.3044,16.8066 27.4962,17.0047 27.4962,17.0047C26.72,16.2274 25.0761,16.6846 25.0761,16.6846Z">
                <aapt:attr name="android:fillColor">
                    <gradient
                        android:endX="27.4962"
                        android:endY="18.4077"
                        android:startX="12.6621"
                        android:startY="18.4077"
                        android:type="linear">
                        <item
                            android:color="#FFFF452A"
                            android:offset="0" />
                        <item
                            android:color="#FFFF2000"
                            android:offset="1" />
                    </gradient>
                </aapt:attr>
            </path>
        </group>
    </group>
</vector>
